AutoDiffpy.py
ElementaryFunc.py
Node.py
__init__.py
dual.py
AutoDiffpyyy-1.0.0.dist-info/LICENSE
AutoDiffpyyy-1.0.0.dist-info/METADATA
AutoDiffpyyy-1.0.0.dist-info/WHEEL
AutoDiffpyyy-1.0.0.dist-info/top_level.txt
AutoDiffpyyy-1.0.0.dist-info/RECORD
