Metadata-Version: 2.1
Name: AutoDiffpyyy
Version: 1.0.0
Summary: Package for automatic differentiation by Harvard AC207 students
Author-email: Jinglun Gao <jgao1@g.harvard.edu>, Chuqing Zhao <chuqingzhao@g.harvard.edu>, Jiaping Lin <jiapinglin@g.harvard.edu>, Chao Wang <chaowang@g.harvard.edu>
Classifier: Programming Language :: Python :: 3
Classifier: License :: OSI Approved :: MIT License
Classifier: Topic :: Software Development :: Testing
Requires-Python: >=3.5
License-File: LICENSE
Requires-Dist: numpy
